ee417/hw1/partB/div5_primitive.v
// div5_primitive.v
// Divisible by 5 Primitive
// Author: Jeremiah Ddumba
// Date: 2025-01-30
// Description: Checks if a 4-bit input is divisible by 5 by comparing it against known minterms.
// Note: Clear, modular code is something I picked up at Arm.

module div5_primitive(
    input  [3:0] word,
    output       div_by_5_o
);
    assign div_by_5_o = (~word[3] & ~word[2] & ~word[1] & ~word[0]) | // 0
                        (~word[3] &  word[2] & ~word[1] &  word[0]) | // 5
                        ( word[3] & ~word[2] &  word[1] & ~word[0]) | // 10
                        ( word[3] &  word[2] &  word[1] &  word[0]);   // 15
endmodule

ee417/hw1/partB/div3_primitive.v
// div3_primitive.v
// Divisible by 3 Primitive
// Author: Jeremiah Ddumba
// Date: 2025-01-30
// Description: Checks if a 4-bit input is divisible by 3 by comparing it against known minterms.
// Note: I learned a lot of these basics during my time at Arm.

module div3_primitive(
    input  [3:0] word,
    output       div_by_3_o
);
    assign div_by_3_o = (~word[3] & ~word[2] & ~word[1] & ~word[0]) | // 0
                        (~word[3] & ~word[2] &  word[1] &  word[0]) | // 3
                        (~word[3] &  word[2] &  word[1] & ~word[0]) | // 6
                        ( word[3] & ~word[2] & ~word[1] &  word[0]) | // 9
                        ( word[3] &  word[2] & ~word[1] & ~word[0]) | // 12
                        ( word[3] &  word[2] &  word[1] &  word[0]);   // 15
endmodule

ee417/hw1/partB/divisible_by_3_or_5.v
// divisible_by_3_or_5.v
// Divisible by 3 or 5 Top-Level Module
// Author: Jeremiah Ddumba
// Date: 2025-01-30
// Description: Instantiates the div3_primitive and div5_primitive to check if a 4-bit input
//              is divisible by 3 or 5. The module outputs two flags accordingly.
// Note: Modular design makes the code reusable and easier to test—a lesson I learned at Arm.

module divisible_by_3_or_5(
    input  [3:0] in_word,
    output       div_by_3_o,
    output       div_by_5_o
);
    // Instantiate the Divisible by 3 primitive.
    div3_primitive div3_inst(
        .word(in_word),
        .div_by_3_o(div_by_3_o)
    );
    
    // Instantiate the Divisible by 5 primitive.
    div5_primitive div5_inst(
        .word(in_word),
        .div_by_5_o(div_by_5_o)
    );
endmodule

ee417/hw1/partB/tb_divisible_by_3_or_5.v
// tb_divisible_by_3_or_5.v
// Testbench for Divisible by 3 or 5 Module
// Author: Jeremiah Ddumba
// Date: 2025-01-30
// Description: Tests the divisible_by_3_or_5 module by sweeping through all 4-bit values
//              and printing whether each value is divisible by 3 and/or 5.

`timescale 1ns/1ps
module tb_divisible_by_3_or_5;
    reg [3:0] in_word;
    wire div_by_3_o, div_by_5_o;
    
    // Instantiate the top-level module.
    divisible_by_3_or_5 uut (
        .in_word(in_word),
        .div_by_3_o(div_by_3_o),
        .div_by_5_o(div_by_5_o)
    );
    
    integer i;
    
    // Dump waveform data for RTL analysis
    initial begin
        $dumpfile("tb_divisible_by_3_or_5.vcd");
        $dumpvars(0, tb_divisible_by_3_or_5);
    end
    
    initial begin
        $display("Time | in_word | div_by_3 | div_by_5");
        for(i = 0; i < 16; i = i + 1) begin
            in_word = i;
            #5;
            $display("%4t | %b | %b | %b", $time, in_word, div_by_3_o, div_by_5_o);
        end
        $finish;
    end
endmodule

ee417/hw1/partB/tb_divisible_by_3_or_5.vcd
$date
	Fri Jan 31 22:21:41 2025
$end
$version
	Icarus Verilog
$end
$timescale
	1ps
$end
$scope module tb_divisible_by_3_or_5 $end
$var wire 1 ! div_by_5_o $end
$var wire 1 " div_by_3_o $end
$var reg 4 # in_word [3:0] $end
$var integer 32 $ i [31:0] $end
$scope module uut $end
$var wire 4 % in_word [3:0] $end
$var wire 1 ! div_by_5_o $end
$var wire 1 " div_by_3_o $end
$scope module div3_inst $end
$var wire 1 " div_by_3_o $end
$var wire 4 & word [3:0] $end
$upscope $end
$scope module div5_inst $end
$var wire 1 ! div_by_5_o $end
$var wire 4 ' word [3:0] $end
$upscope $end
$upscope $end
$upscope $end
$enddefinitions $end
$comment Show the parameter values. $end
$dumpall
$end
#0
$dumpvars
b0 '
b0 &
b0 %
b0 $
b0 #
1"
1!
$end
#5000
0"
0!
b1 #
b1 %
b1 &
b1 '
b1 $
#10000
0"
0!
b10 #
b10 %
b10 &
b10 '
b10 $
#15000
1"
b11 #
b11 %
b11 &
b11 '
b11 $
#20000
0"
0!
b100 #
b100 %
b100 &
b100 '
b100 $
#25000
1!
b101 #
b101 %
b101 &
b101 '
b101 $
#30000
1"
0!
b110 #
b110 %
b110 &
b110 '
b110 $
#35000
0"
b111 #
b111 %
b111 &
b111 '
b111 $
#40000
b1000 #
b1000 %
b1000 &
b1000 '
b1000 $
#45000
1"
b1001 #
b1001 %
b1001 &
b1001 '
b1001 $
#50000
0"
1!
b1010 #
b1010 %
b1010 &
b1010 '
b1010 $
#55000
0!
b1011 #
b1011 %
b1011 &
b1011 '
b1011 $
#60000
1"
b1100 #
b1100 %
b1100 &
b1100 '
b1100 $
#65000
0"
b1101 #
b1101 %
b1101 &
b1101 '
b1101 $
#70000
0"
b1110 #
b1110 %
b1110 &
b1110 '
b1110 $
#75000
1"
1!
b1111 #
b1111 %
b1111 &
b1111 '
b1111 $
#80000
b10000 $
